LICENSE
MANIFEST.in
README.rst
setup.py
change_case/__init__.py
change_case/change_case.py
change_case.egg-info/PKG-INFO
change_case.egg-info/SOURCES.txt
change_case.egg-info/dependency_links.txt
change_case.egg-info/top_level.txt
change_case/__pycache__/__init__.cpython-34.pyc
change_case/__pycache__/change_case.cpython-34.pyc